setup.py
probadist/Binomialdistribution.py
probadist/Gaussiandistribution.py
probadist/Generaldistribution.py
probadist/__init__.py
probadist.egg-info/PKG-INFO
probadist.egg-info/SOURCES.txt
probadist.egg-info/dependency_links.txt
probadist.egg-info/not-zip-safe
probadist.egg-info/top_level.txt