Metadata-Version: 1.0
Name: probadist
Version: 0.1
Summary: Probability distributions
Home-page: UNKNOWN
Author: Lavinan Selvaratnam
Author-email: lavinan26@gmail.com
License: UNKNOWN
Platform: UNKNOWN
